maticlib/__init__.py
maticlib/utils.py
maticlib/client/__init__.py
maticlib/client/classes/base_client.py
maticlib/client/classes/client_output_model.py
maticlib/client/classes/enums/modality_type.py
maticlib/client/classes/enums/role_type.py
maticlib/client/classes/model_classes/content_part.py
maticlib/core/__init__.py
maticlib/core/prompt/format.py
maticlib/examples/maticgraph/ex1.py
maticlib/examples/maticgraph/ex2.py
maticlib/examples/maticgraph/ex3.py
maticlib/examples/messages/test.py
maticlib/examples/messages/test1.py
maticlib/examples/messages/test2.py
maticlib/graph/__init__.py
maticlib/graph/graph.py
maticlib/graph/node.py
maticlib/llm/__init__.py
maticlib/llm/google_genai/__init__.py
maticlib/llm/google_genai/client.py
maticlib/llm/google_genai/gemini_classes.py
maticlib/llm/mistral/__init__.py
maticlib/llm/mistral/client.py
maticlib/llm/mistral/mistral_classes.py
maticlib/messages/__init__.py
maticlib/messages/ai_message.py
maticlib/messages/errors.py
maticlib/messages/human_message.py
maticlib/messages/message.py
maticlib/messages/system_message.py
maticlib/messages/types.py
maticlib/tests/__init__.py
maticlib/tests/test_client.py
maticlib-0.1.4.dist-info/licenses/LICENSE
maticlib-0.1.4.dist-info/METADATA
maticlib-0.1.4.dist-info/WHEEL
maticlib-0.1.4.dist-info/top_level.txt
maticlib-0.1.4.dist-info/RECORD
