Metadata-Version: 2.4
Name: maticlib
Version: 0.1.4
Summary: A Python Automation Library for creating agents
Author-email: Arvoh Software <arvohsoft@gmail.com>
License-Expression: MIT
Project-URL: Homepage, https://github.com/arvohsoft/maticlib.git
Project-URL: Repository, https://github.com/arvohsoft/maticlib.git
Requires-Python: >=3.8
License-File: LICENSE
Requires-Dist: httpx>=0.24.0
Requires-Dist: pydantic
Provides-Extra: dev
Requires-Dist: pytest>=7.0.0; extra == "dev"
Requires-Dist: pytest-asyncio>=0.21.0; extra == "dev"
Requires-Dist: black>=23.0.0; extra == "dev"
Requires-Dist: mypy>=1.0.0; extra == "dev"
Dynamic: license-file
